[
    {
      "KingOfName": "鼠",
      "RefreshTick": "5",
      "Die": "2016-06-30 16:09:51",
      "Resurrection": "2016-06-30 21:09:51"
    },
    {
      "KingOfName": "牛",
      "RefreshTick": "6",
      "Die": "2016-06-30 16:09:51",
      "Resurrection": "2016-06-30 22:09:51"
    },
    {
      "KingOfName": "虎",
      "RefreshTick": "7",
      "Die": "2016-06-30 16:09:51",
      "Resurrection": "2016-06-30 23:09:51"
    },
    {
      "KingOfName": "兔",
      "RefreshTick": "8",
      "Die": "2016-06-30 16:09:51",
      "Resurrection": "2016-07-01 00:09:51"
    }
]
